discrete_morphology
