Metadata-Version: 1.0
Name: discrete-morphology
Version: 1.0.1
Summary: Set of algorithms in the framework of discrete mathematical morphology for image processing.
Home-page: https://github.com/mmunar97/discrete_morphology
Author: marcmunar
Author-email: marc.munar@uib.es
License: mit
Platform: UNKNOWN
